brainbase/__init__.py
brainbase/client.py
brainbase/connection.py
brainbase/exceptions.py
brainbase/json_client.py
brainbase/models.py
brainbase/utils.py
brainbase_engine-0.1.1.dist-info/LICENSE
brainbase_engine-0.1.1.dist-info/METADATA
brainbase_engine-0.1.1.dist-info/WHEEL
brainbase_engine-0.1.1.dist-info/top_level.txt
brainbase_engine-0.1.1.dist-info/RECORD
